{
  "$schema": "https://json-schema.org/draft/2020-12/schema",
  "$id": "https://ai-software-studio.local/studio-loop/planner-output.schema.json",
  "type": "object",
  "additionalProperties": false,
  "required": ["schema_version", "status", "spec_markdown", "plan_markdown", "tasks", "ambiguities", "blocking_issues"],
  "properties": {
    "schema_version": {"const": "1.1.0"},
    "status": {"enum": ["ready", "blocked", "failed"]},
    "spec_markdown": {"type": "string", "minLength": 1, "maxLength": 100000},
    "plan_markdown": {"type": "string", "minLength": 1, "maxLength": 100000},
    "tasks": {"type": "object", "minProperties": 1},
    "ambiguities": {"$ref": "#/$defs/findings"},
    "blocking_issues": {"$ref": "#/$defs/findings"}
  },
  "$defs": {
    "findings": {"type": "array", "maxItems": 64, "items": {"type": "string", "minLength": 1, "maxLength": 2000}}
  }
}
